bookocr/__init__.py
bookocr/_char_ocr.py
bookocr/_json.py
bookocr/_service.py
bookocr/_stats.py
bookocr/config.py
bookocr/model.h5
bookocr/ocr.py
bookocr/stats_config.py
bookocr-1.0.3.dist-info/LICENSE
bookocr-1.0.3.dist-info/METADATA
bookocr-1.0.3.dist-info/WHEEL
bookocr-1.0.3.dist-info/top_level.txt
bookocr-1.0.3.dist-info/RECORD
