Metadata-Version: 2.1
Name: bookocr
Version: 1.0.3
Summary: Optical character recognition (OCR) tool for printed book pages
Author-email: Artem Poliakov <artem4250@gmail.com>
Project-URL: Homepage, https://github.com/Artem259/bookocr
Classifier: Programming Language :: Python :: 3
Classifier: License :: OSI Approved :: MIT License
Classifier: Operating System :: OS Independent
Requires-Python: >=3.9
License-File: LICENSE
Requires-Dist: opencv-python (>=4.5.5.64)
Requires-Dist: numpy (>=1.23.5)
Requires-Dist: pandas (>=2.0.1)
Requires-Dist: scipy (>=1.10.1)
Requires-Dist: tensorflow (>=2.12.0)
Requires-Dist: Pillow (>=9.5.0)
